{
    "components": {
        "main": "masterworks:material"
    },
    "properties": {
        "masterworks:item": {
            "masterworks:render_item": "masterworks:pickaxe/head",
            "masterworks:durability": "$main * 0.5",
            "masterworks:mining_denied": "$main",
            "masterworks:mining_speed": "$main * 0.3",
            "masterworks:attack_damage": "$main + -2",
            "masterworks:attack_speed": "$main * 0.3"
        },
        "masterworks:component/pickaxe_head": {
            "masterworks:render_item": "masterworks:pickaxe/head",
            "masterworks:durability": "$main * 0.5",
            "masterworks:mining_denied": "$main",
            "masterworks:mining_speed": "$main * 0.3",
            "masterworks:attack_damage": "$main + -2",
            "masterworks:attack_speed": "$main * 0.3"
        }
    }
}